{"chunk_definitions":[{"row":18,"row_count":1,"visible":true,"expansion_state":0,"options":{"engine":"r","label":"setup","include":false},"document_id":"A94A3E49","chunk_id":"csetup_chunk","chunk_label":"setup"},{"row":44,"row_count":1,"visible":true,"expansion_state":0,"options":{"engine":"r","label":"unnamed-chunk-622"},"document_id":"A94A3E49","chunk_id":"cro121do0m06l","chunk_label":"unnamed-chunk-1"},{"row":66,"row_count":1,"visible":true,"expansion_state":0,"options":{"engine":"r","label":"unnamed-chunk-623"},"document_id":"A94A3E49","chunk_id":"cz19uj72gp7k6","chunk_label":"unnamed-chunk-2"},{"row":105,"row_count":1,"visible":true,"expansion_state":0,"options":{"engine":"r","label":"unnamed-chunk-624"},"document_id":"A94A3E49","chunk_id":"cnvoy6spsnw3n","chunk_label":"unnamed-chunk-5"},{"row":134,"row_count":1,"visible":true,"expansion_state":0,"options":{"engine":"r","label":"unnamed-chunk-626"},"document_id":"A94A3E49","chunk_id":"csvep2pbchq7v","chunk_label":"unnamed-chunk-6"},{"row":147,"row_count":1,"visible":true,"expansion_state":0,"options":{"engine":"r","label":"unnamed-chunk-627"},"document_id":"A94A3E49","chunk_id":"ca33j9n6djmqy","chunk_label":"unnamed-chunk-7"},{"row":174,"row_count":1,"visible":true,"expansion_state":0,"options":{"warning":false,"engine":"r","label":"unnamed-chunk-629"},"document_id":"A94A3E49","chunk_id":"cae5lrmu6lskb","chunk_label":"unnamed-chunk-8"},{"row":219,"row_count":1,"visible":true,"expansion_state":0,"options":{"warning":false,"engine":"r","label":"unnamed-chunk-631"},"document_id":"A94A3E49","chunk_id":"ccuvywjahh0cy","chunk_label":"unnamed-chunk-10"}],"doc_write_time":1681512934,"working_dir":null,"default_chunk_options":{},"chunk_rendered_width":700}